pypuyo/__init__.py
pypuyo/pypuyo.py
pypuyo-1.0.4.dist-info/LICENSE
pypuyo-1.0.4.dist-info/METADATA
pypuyo-1.0.4.dist-info/WHEEL
pypuyo-1.0.4.dist-info/top_level.txt
pypuyo-1.0.4.dist-info/RECORD
