Metadata-Version: 2.1
Name: pypuyo
Version: 1.0.4
Summary: A package to make Puyo-Puyo-ish games.
Author-email: nnamaco <eureka5129@gmail.com>
License: MIT License        
Project-URL: Homepage, https://github.com/nnmaco/pypuyo
Project-URL: Bug Tracker, https://github.com/nnmaco/pypuyo/issues
Classifier: Programming Language :: Python :: 3
Classifier: License :: OSI Approved :: MIT License
Classifier: Operating System :: OS Independent
Requires-Python: >=3.7
License-File: LICENSE
